ii0703_ejemplo_pypi0c2025/__init__.py
ii0703_ejemplo_pypi0c2025/main.py
ii0703_ejemplo_pypi0c2025-0.0.1.dist-info/METADATA
ii0703_ejemplo_pypi0c2025-0.0.1.dist-info/WHEEL
ii0703_ejemplo_pypi0c2025-0.0.1.dist-info/entry_points.txt
ii0703_ejemplo_pypi0c2025-0.0.1.dist-info/top_level.txt
ii0703_ejemplo_pypi0c2025-0.0.1.dist-info/RECORD
